MANIFEST.in
README.rst
setup.py
clearwind/__init__.py
clearwind.arecibo.egg-info/PKG-INFO
clearwind.arecibo.egg-info/SOURCES.txt
clearwind.arecibo.egg-info/dependency_links.txt
clearwind.arecibo.egg-info/entry_points.txt
clearwind.arecibo.egg-info/namespace_packages.txt
clearwind.arecibo.egg-info/not-zip-safe
clearwind.arecibo.egg-info/requires.txt
clearwind.arecibo.egg-info/top_level.txt
clearwind/arecibo/__init__.py
clearwind/arecibo/config.py
clearwind/arecibo/configure.zcml
clearwind/arecibo/exportimport.py
clearwind/arecibo/interfaces.py
clearwind/arecibo/patch.py
clearwind/arecibo/setuphandlers.py
clearwind/arecibo/site_configuration.py.in
clearwind/arecibo/tests.py
clearwind/arecibo/version.txt
clearwind/arecibo/wrapper.py
clearwind/arecibo/Extensions/Install.py
clearwind/arecibo/browser/__init__.py
clearwind/arecibo/browser/arecibo-icon.png
clearwind/arecibo/browser/config.py
clearwind/arecibo/browser/configure.zcml
clearwind/arecibo/lib/LICENSE.txt
clearwind/arecibo/lib/README.txt
clearwind/arecibo/lib/__init__.py
clearwind/arecibo/lib/arecibo.py
clearwind/arecibo/lib/simplejson/__init__.py
clearwind/arecibo/lib/simplejson/_speedups.c
clearwind/arecibo/lib/simplejson/decoder.py
clearwind/arecibo/lib/simplejson/encoder.py
clearwind/arecibo/lib/simplejson/scanner.py
clearwind/arecibo/lib/simplejson/tool.py
clearwind/arecibo/profiles/default/actionicons.xml
clearwind/arecibo/profiles/default/clearwind.arecibo.txt
clearwind/arecibo/profiles/default/controlpanel.xml
docs/HISTORY.rst
docs/INSTALL.rst
docs/LICENSE.GPL
docs/LICENSE.txt