Metadata-Version: 1.0
Name: clearwind.arecibo
Version: 0.7
Summary: Connector from Plone to Arecibo
Home-page: http://clearwind.ca
Author: ClearWind Consulting
Author-email: andy@clearwind.ca
License: BSD
Platform: UNKNOWN
Classifier: Framework :: Plone
Classifier: Programming Language :: Python
Classifier: Topic :: Software Development :: Libraries :: Python Modules
